Metadata-Version: 2.1
Name: wikivoyage
Version: 0.2
Summary: Consume Wikivoyage pages into pure (elegant) Markdown. Probably.
Author-email: AWeirdDev <aweirdscratcher@gmail.com>
License: MIT License
Project-URL: Source, https://github.com/AWeirdScratcher/wikivoyage
Project-URL: Bug Tracker, https://github.com/AWeirdScratcher/wikivoyage/issues
Keywords: wikivoyage,wikipedia,wiki,requests,info,markdown,selectolax,parser
Classifier: Programming Language :: Python :: 3
Classifier: License :: OSI Approved :: MIT License
Classifier: Operating System :: OS Independent
Requires-Python: >=3.8
License-File: LICENSE
Requires-Dist: selectolax
Requires-Dist: requests
